{"assets":{"56286BD956D3A3DD87B04BCF3FD125FA":{"type":"texture","index":0,"assetRequest":{"type":"slide","state":"contents","slide":"none"},"url":{"native":"assets\/82BA46A4-A5CE-4DE5-8CBC-38A8225B52ED.pdf"},"width":1920,"height":1080},"F34FD7E24FE4A3F5A6127DC86AB9EF9C":{"type":"texture","index":1,"assetRequest":{"type":"slide","state":"contents","slide":"none"},"url":{"native":"assets\/82BA46A4-A5CE-4DE5-8CBC-38A8225B52ED.pdf"},"width":1920,"height":1080}},"events":[{"effects":[{"beginTime":0,"baseLayer":{"animations":[],"initialState":{"affineTransform":[1,0,0,1,0,0],"masksToBounds":false,"rotation":0,"scale":1,"position":{"pointX":960,"pointY":540},"width":1920,"sublayerTransform":[1,0,0,0,0,1,0,0,0,0,1,0,0,0,0,1],"contentsRect":{"y":0,"x":0,"width":1,"height":1},"opacity":1,"edgeAntialiasingMask":251658240,"height":1080,"hidden":false,"anchorPoint":{"pointX":0.5,"pointY":0.5}},"objectID":"0","layers":[{"animations":[],"initialState":{"affineTransform":[1,0,0,1,0,0],"masksToBounds":false,"rotation":0,"scale":1,"position":{"pointX":960,"pointY":540},"width":1920,"sublayerTransform":[1,0,0,0,0,1,0,0,0,0,1,-0.00035007912466775983,0,0,0,1],"contentsRect":{"y":0,"x":0,"width":1,"height":1},"opacity":1,"edgeAntialiasingMask":251658240,"height":1080,"hidden":false,"anchorPoint":{"pointX":0.5,"pointY":0.5}},"layers":[{"animations":[],"layers":[],"texturedRectangle":{"isBackgroundTexture":false,"singleTextureOpacity":1,"textureType":0,"textBaseline":0,"textXHeight":0,"isVerticalText":false},"initialState":{"affineTransform":[1,0,0,1,0,0],"masksToBounds":false,"rotation":0,"scale":1,"position":{"pointX":960,"pointY":540},"width":1920,"sublayerTransform":[1,0,0,0,0,1,0,0,0,0,1,0,0,0,0,1],"contentsRect":{"y":0,"x":0,"width":1,"height":1},"opacity":1,"edgeAntialiasingMask":0,"height":1080,"hidden":false,"anchorPoint":{"pointX":0.5,"pointY":0.5}},"texture":"F34FD7E24FE4A3F5A6127DC86AB9EF9C"},{"animations":[{"additive":false,"timeOffset":0,"beginTime":0,"from":{"scalar":false},"repeatCount":0,"fillMode":"both","duration":0.01,"autoreverses":false,"property":"hidden","to":{"scalar":true},"removedOnCompletion":false}],"layers":[],"texturedRectangle":{"isBackgroundTexture":false,"singleTextureOpacity":1,"textureType":0,"textBaseline":0,"textXHeight":0,"isVerticalText":false},"initialState":{"affineTransform":[1,0,0,1,0,0],"masksToBounds":false,"rotation":0,"scale":1,"position":{"pointX":960,"pointY":540},"width":1920,"sublayerTransform":[1,0,0,0,0,1,0,0,0,0,1,0,0,0,0,1],"contentsRect":{"y":0,"x":0,"width":1,"height":1},"opacity":1,"edgeAntialiasingMask":0,"height":1080,"hidden":false,"anchorPoint":{"pointX":0.5,"pointY":0.5}},"texture":"56286BD956D3A3DD87B04BCF3FD125FA"}]}]},"effects":[],"duration":0.01,"type":"transition","attributes":{"direction":0},"name":"none","objectID":"0"}],"automaticPlay":false,"hyperlinks":[],"accessibility":[{"text":"￼","targetRectangle":{"y":55.5625,"x":790.22705042362213,"width":26.3916015625,"height":30}},{"text":"pasted-image.pdf","targetRectangle":{"y":1.5640531778335571,"x":1511.24658203125,"width":409.05599975585938,"height":411.3900146484375}},{"text":"Design Strategy","targetRectangle":{"y":178.22550964355469,"x":109.85548400878906,"width":382,"height":59}},{"text":"www.mohanpatcha.com","targetRectangle":{"y":995.44879126548767,"x":55.443485260009766,"width":279.62400000000008,"height":29}},{"text":"Business Goals","targetRectangle":{"y":365.28799438476562,"x":138.70163702964783,"width":209.43574209697545,"height":62.400000929832458}},{"text":"Hassle Free Finding Parking system for all the Citizens and Cab Drivers ","targetRectangle":{"y":427.68799531459808,"x":183.81381642818451,"width":767.11899963242581,"height":35.099998712539673}},{"text":"Enhancing the Citizens business experience","targetRectangle":{"y":462.78799402713776,"x":183.81381642818451,"width":473.86899978665247,"height":35.099998712539673}},{"text":"Partner with more Parking bay providers to get the services Onboard ","targetRectangle":{"y":497.88799273967743,"x":183.81381642818451,"width":745.31499965298917,"height":35.099998712539673}},{"text":"User Groups","targetRectangle":{"y":532.9879914522171,"x":138.70163702964783,"width":167.78378899209201,"height":62.400000929832458}},{"text":"Citizens ","targetRectangle":{"y":595.38799238204956,"x":183.81381642818451,"width":90.435999956302339,"height":35.099998712539673}},{"text":"Drivers","targetRectangle":{"y":630.48799109458923,"x":183.81381642818451,"width":75.646999966584133,"height":35.099998712539673}},{"text":"Parking providers","targetRectangle":{"y":665.58798980712891,"x":183.81381642818451,"width":188.55399991517515,"height":35.099998712539673}},{"text":"General Tasks","targetRectangle":{"y":700.68798851966858,"x":138.70163702964783,"width":191.23535147868097,"height":62.400000929832458}},{"text":"Finding the Parking area","targetRectangle":{"y":763.08798944950104,"x":183.81381642818451,"width":262.19999987918885,"height":35.099998712539673}},{"text":"Book the parking bay","targetRectangle":{"y":798.18798816204071,"x":183.81381642818451,"width":229.70099989461153,"height":35.099998712539673}},{"text":"Paying Parking bills upfront ","targetRectangle":{"y":833.28798687458038,"x":183.81381642818451,"width":301.50699985348433,"height":35.099998712539673}},{"text":"Parking area providers onBoarding ( GHMC, Metro Rail, Railway stations, Airports)","targetRectangle":{"y":868.38798558712006,"x":183.81381642818451,"width":869.51499958358727,"height":35.099998712539673}},{"text":"MOHAN PATCHA","targetRectangle":{"y":56.062500238418579,"x":57.692340850830078,"width":205.66000000000003,"height":30}},{"text":"Understanding the broader picture of the applications is done and the information is visualized, Based on the assignment documentation, a design strategy has been formulated ","targetRectangle":{"y":250.35407149791718,"x":109.85548400878906,"width":1506.5919992905556,"height":70.199997425079346}}],"baseLayer":{"animations":[],"initialState":{"affineTransform":[1,0,0,1,0,0],"masksToBounds":false,"rotation":0,"scale":1,"position":{"pointX":960,"pointY":540},"width":1920,"sublayerTransform":[1,0,0,0,0,1,0,0,0,0,1,0,0,0,0,1],"contentsRect":{"y":0,"x":0,"width":1,"height":1},"opacity":1,"edgeAntialiasingMask":251658240,"height":1080,"hidden":false,"anchorPoint":{"pointX":0.5,"pointY":0.5}},"objectID":"0","layers":[{"animations":[],"initialState":{"affineTransform":[1,0,0,1,0,0],"masksToBounds":false,"rotation":0,"scale":1,"position":{"pointX":960,"pointY":540},"width":1920,"sublayerTransform":[1,0,0,0,0,1,0,0,0,0,1,-0.00035007912466775983,0,0,0,1],"contentsRect":{"y":0,"x":0,"width":1,"height":1},"opacity":1,"edgeAntialiasingMask":251658240,"height":1080,"hidden":false,"anchorPoint":{"pointX":0.5,"pointY":0.5}},"layers":[{"animations":[],"layers":[],"texturedRectangle":{"isBackgroundTexture":false,"singleTextureOpacity":1,"textureType":0,"textBaseline":0,"textXHeight":0,"isVerticalText":false},"initialState":{"affineTransform":[1,0,0,1,0,0],"masksToBounds":false,"rotation":0,"scale":1,"position":{"pointX":960,"pointY":540},"width":1920,"sublayerTransform":[1,0,0,0,0,1,0,0,0,0,1,0,0,0,0,1],"contentsRect":{"y":0,"x":0,"width":1,"height":1},"opacity":1,"edgeAntialiasingMask":0,"height":1080,"hidden":false,"anchorPoint":{"pointX":0.5,"pointY":0.5}},"texture":"56286BD956D3A3DD87B04BCF3FD125FA"}]}]}}]}